{
  "code": 200,
  "status": "OK",
  "data": {
    "number": 113,
    "name": "سُورَةُ الفَلَقِ",
    "englishName": "Al-Falaq",
    "englishNameTranslation": "The Dawn",
    "revelationType": "Meccan",
    "numberOfAyahs": 5,
    "ayahs": [
      {
        "number": 6226,
        "text": "কুল আ‘ঊযুবিরাব্বিল ফালাক",
        "numberInSurah": 1,
        "juz": 30,
        "manzil": 7,
        "page": 604,
        "ruku": 555,
        "hizbQuarter": 240,
        "sajda": false
      },
      {
        "number": 6227,
        "text": "মিন শাররি মা-খালাক।",
        "numberInSurah": 2,
        "juz": 30,
        "manzil": 7,
        "page": 604,
        "ruku": 555,
        "hizbQuarter": 240,
        "sajda": false
      },
      {
        "number": 6228,
        "text": "ওয়া মিন শাররি গা-ছিকিন ইযা-ওয়াকাব।",
        "numberInSurah": 3,
        "juz": 30,
        "manzil": 7,
        "page": 604,
        "ruku": 555,
        "hizbQuarter": 240,
        "sajda": false
      },
      {
        "number": 6229,
        "text": "ওয়া মিন শাররিন নাফফা-ছা-তি ফিল ‘উকাদ।",
        "numberInSurah": 4,
        "juz": 30,
        "manzil": 7,
        "page": 604,
        "ruku": 555,
        "hizbQuarter": 240,
        "sajda": false
      },
      {
        "number": 6230,
        "text": "ওয়া মিন শাররি হা-ছিদিন ইযা-হাছাদ।",
        "numberInSurah": 5,
        "juz": 30,
        "manzil": 7,
        "page": 604,
        "ruku": 555,
        "hizbQuarter": 240,
        "sajda": false
      }
    ],
    "edition": {
      "identifier": "quran-uthmani-quran-academy",
      "language": "ar",
      "name": "القرآن الكريم برسم العثماني (quran-academy)",
      "englishName": "Modified Quran Uthmani Text from the Quran Academy to work with the Kitab font",
      "format": "text",
      "type": "quran",
      "direction": "rtl"
    }
  }
}