{
  "code": 200,
  "status": "OK",
  "data": {
    "number": 21,
    "ayahs": [
      {
        "numberInSurah": 1,
        "pronunciation": "ইকতারাবা লিন্না-ছি হিছা-বুহুম ওয়া হুম ফী গাফলাতিম মু‘রিদূন।"
      },
      {
        "numberInSurah": 2,
        "pronunciation": "মা-ইয়া’তীহিম মিন যিকরিম মির রাব্বিহিম মুহদাছিন ইল্লাছতামা‘উহু ওয়া হুম ইয়াল‘আবূন।"
      },
      {
        "numberInSurah": 3,
        "pronunciation": "লা-হিয়াতান কুলূবুহুম ওয়া আছার রুন নাজওয়াল্লাযীনা জালামূ হাল হা-যা ইল্লা-বাশারুম মিছলুকুম আফাতা’তূনাছছিহরা ওয়া আনতুম তুবসিরূন।"
      },
      {
        "numberInSurah": 4,
        "pronunciation": "কা-লা রাববী ইয়া‘লামুল কাওলা ফিছছামাই ওয়াল আরদি ওয়া হুওয়াছছামী‘উল ‘আলীম।"
      },
      {
        "numberInSurah": 5,
        "pronunciation": "বাল কা-লূআদগা-ছু আহলা-মিম বালিফ তারা-হু বাল হুওয়া শা-‘ইরুন ফালইয়া’তিনা-বিআ-য়াতিন কামাউরছিলাল আওওয়ালূন।"
      },
      {
        "numberInSurah": 6,
        "pronunciation": "মাআ-মানাত কাবলাহুম মিন কারইয়াতিন আহলাকনা-হা- আফাহুম ইউ’মিনূন।"
      },
      {
        "numberInSurah": 7,
        "pronunciation": "ওয়ামাআরছালনা-কাবলাকা ইল্লা-রিজা-লাননূহীইলাইহিম ফাছআলূআহলাযযিকরি ইন কুনতুম লা-তা‘লামূন।"
      },
      {
        "numberInSurah": 8,
        "pronunciation": "ওয়ামা-জা‘আলনা-হুম জাছাদাল্লা-ইয়া‘কুলূনাততা‘আ-মা ওয়ামা-কা-নূখা-লিদীন।"
      },
      {
        "numberInSurah": 9,
        "pronunciation": "ছু ম্মা সাদাকনা-হুমুল ওয়া‘দা ফাআনজাইনা-হুম ওয়া মান নাশাউ ওয়া আহলাকনাল মুছরিফীন।"
      },
      {
        "numberInSurah": 10,
        "pronunciation": "লাকাদ আনঝালনাইলাইকুম কিতা-বান ফীহি যিকরুকুম আফালা-তা‘কিলূন।"
      },
      {
        "numberInSurah": 11,
        "pronunciation": "ওকাম কাসামনা- মিন কারইয়াতিন কা-নাত জা-লিমাতাওঁ ওয়া আনশা’না- বা‘দাহাকাওমান আ-খারীন।"
      },
      {
        "numberInSurah": 12,
        "pronunciation": "ফালাম্মাআহাছছূবা’ছানাইযা-হুম মিনহা-ইয়ারকুদূন।"
      },
      {
        "numberInSurah": 13,
        "pronunciation": "লা- তারকুদূ ওয়ারজি‘উ ইলা-মাউতরিফতুম ফীহি ওয়া মাছা-কিনিকুম লা‘আল্লাকুম তুছআলূন।"
      },
      {
        "numberInSurah": 14,
        "pronunciation": "কা-লূইয়া-ওয়াইলানাইন্না-কুন্না-জা-লিমীন।"
      },
      {
        "numberInSurah": 15,
        "pronunciation": "ফামা-ঝা-লাত তিলকা দা‘ওয়া-হুম হাত্তা-জা‘আলনা-হুম হাসীদান খা-মিদীন।"
      },
      {
        "numberInSurah": 16,
        "pronunciation": "ওয়ামা-খালাকনাছছামাআ ওয়াল আরদা ওয়ামা-বাইনাহুমা-লা-‘ইবীন।"
      },
      {
        "numberInSurah": 17,
        "pronunciation": "লাও আরাদনাআন নাত্তাখিযা লাহওয়াল্লাত্তাখাযনা -হু মিল্লাদুন্না  ইন কুন্না-ফা-‘ইলীন ।"
      },
      {
        "numberInSurah": 18,
        "pronunciation": "বাল নাকযিফুবিলহাক্কি‘আলাল বা-তিলি ফাইয়াদমাগুহূফাইযা-হুওয়া ঝা-হিকুও ওয়ালাকুমুল ওয়াইলুমিম্মা-তাসিফূন।"
      },
      {
        "numberInSurah": 19,
        "pronunciation": "ওয়া লাহূমান ফিছছামা-ওয়া-তি ওয়াল আরদি;ওয়ামান ‘ইন্দাহূলা-ইয়াছতাকবিরূনা ‘আন ‘ইবা-দাতিহী ওয়ালা-ইয়াছতাহছিরূন।"
      },
      {
        "numberInSurah": 20,
        "pronunciation": "ইউছাব্বিহূ নাল লাইলা ওয়ান নাহা-রা লা-ইয়াফতুরূন।"
      },
      {
        "numberInSurah": 21,
        "pronunciation": "আমিততাখাযূআ-লিহাতাম মিনাল আরদিহুম ইউনশিরূন।"
      },
      {
        "numberInSurah": 22,
        "pronunciation": "লাও কা-না ফীহিমাআ-লিহাতুন ইল্লাল্লা-হু লাফাছাদাতা- ফাছুবহা-নাল্লা-হি রাব্বিল ‘আরশি ‘আম্মা-ইয়াসিফূন।"
      },
      {
        "numberInSurah": 23,
        "pronunciation": "লা-ইউছআলু‘আম্মা-ইয়াফ‘আলুওয়া হুম ইউছআলূন।"
      },
      {
        "numberInSurah": 24,
        "pronunciation": "আমিত তাখাযূমিন দূ নিহীআ-লিহাতান কুল হা-তূবুরহা-নাকুম হা-যা-যিকরু মাম মা‘ইয়া ওয়া যিকরু মান কাবলী বাল আকছারুহুম লা-ইয়া‘লামূনাল হাক্কা ফাহুম মু‘রিদূ ন।"
      },
      {
        "numberInSurah": 25,
        "pronunciation": "ওয়ামাআরছালনা-মিন কাবলিকা মির রাছূলিন ইল্লা-নূহীইলাইহি আন্নাহূলাইলা-হা ইল্লাআনা-ফা‘বুদূন।"
      },
      {
        "numberInSurah": 26,
        "pronunciation": "ওয়া কা-লুততাখাযার রাহমা-নুওয়ালাদান ছুবহা-নাহূ বাল ‘ইবা-দুম মুকরামূন।"
      },
      {
        "numberInSurah": 27,
        "pronunciation": "লা-ইয়াছবিকূ নাহূবিলকাওলি ওয়া হুম বিআমরিহী ইয়া‘মালূন।"
      },
      {
        "numberInSurah": 28,
        "pronunciation": "ইয়া‘লামুমা-বাইনা আইদীহিম ওয়ামা-খালফাহুম ওয়ালা-ইয়াশফা‘ঊনা ইল্লালিমানিরতাদা-ওয়া হুম মিন খাশইয়াতিহী মুশফিকূন।"
      },
      {
        "numberInSurah": 29,
        "pronunciation": "ওয়া মাইঁ ইয়াকুল মিনহুম ইন্নীইলা-হুম মিন দূ নিহী ফাযা-লিকা নাজঝীহি জাহান্নামা কাযা-লিকা নাজঝিজ্জা-লিমীন।"
      },
      {
        "numberInSurah": 30,
        "pronunciation": "আওয়ালাম ইয়ারাল্লাযীনা কাফারূআন্নছছামা-ওয়া-তি ওয়াল আরদা কা-নাতা-রাতকান ফাফাতাকনা-হুমা- ওয়া জা‘আলনা-মিনাল মাই কুল্লা শাইয়িন হাইয়ি আফালাইউ’মিনূন।"
      },
      {
        "numberInSurah": 31,
        "pronunciation": "ওয়া জা‘আলনা-ফিল আরদিরাওয়া-ছিয়া আন তামীদা বিহিম ওয়া জা‘আলনা ফীহাফিজাজান ছুবুলাল লা‘আল্লাহুম ইয়াহতাদূ ন।"
      },
      {
        "numberInSurah": 32,
        "pronunciation": "ওয়া জা‘আলনাছছামাআ ছাকফাম মাহফূজাওঁ ওয়া হুম ‘আন আ-য়া-তিহা মু‘রিদূ ন।"
      },
      {
        "numberInSurah": 33,
        "pronunciation": "ওয়াহুয়াল্লাযী খালাকাল লাইলা-ওয়ান্নাহা-রা ওয়াশ শামছা ওয়াল কামারা কুল্লুন ফী ফালাকিইঁ ইয়াছবাহূন।"
      },
      {
        "numberInSurah": 34,
        "pronunciation": "ওয়ামা-জা‘আলনা-লিবাশারিম মিন কাবলিকাল খুলদা আফাইম মিত্তা ফাহুমুল খা-লিদূ ন।"
      },
      {
        "numberInSurah": 35,
        "pronunciation": "কুল্লুনাফছিন যাইকাতুল মাওতি ওয়া নাবলূকুম বিশশাররি ওয়াল খাইরি ফিতনাতাও ওয়া ইলাইনা-তুর জা‘ঊন ।"
      },
      {
        "numberInSurah": 36,
        "pronunciation": "ওয়া ইযা-রাআ-কাল্লাযীনা কাফারূইয়ঁইয়াত্তাখিযূনাকা ইল্লা-হুঝুওয়ান আহাযাল্লাযী ইয়াযকুরু আ-লিহাতাকুম ওয়া হুম বিযিকরির রাহমা-নি হুম কা-ফিরূন।"
      },
      {
        "numberInSurah": 37,
        "pronunciation": "খুলিকাল ইনছা-নুমিন ‘আজালিন ছাঊরীকুম আ-য়া-তী ফালা-তাছতা‘জিলূন।"
      },
      {
        "numberInSurah": 38,
        "pronunciation": "ওয়া-ইয়াকূ লূনা মাতা-হা-যাল ও‘দুইন কুনতুম সা-দিকীন।"
      },
      {
        "numberInSurah": 39,
        "pronunciation": "লাও ইয়া‘লামুল্লাযীনা কাফারূহীনা লা-ইয়াকুফফূনা ‘আওঁউজুহিহিমুন্না-রা ওয়ালা-‘আন জু হূরিহিম ওয়ালা-হুম ইউনসারূন।"
      },
      {
        "numberInSurah": 40,
        "pronunciation": "বাল তা’তীহিম বাগতাতান ফাতাবহাতুহুম, ফালা-ইয়াছতাতী‘উনা রাদ্দাহা-ওয়া লা-হুম ইউনজারূন।"
      },
      {
        "numberInSurah": 41,
        "pronunciation": "ওয়ালাকাদিছ তুহঝিআ বিরুছুলিম মিন কাবলিকা ফাহা-কাবিল্লাযীনা ছাখিরূমিনহুম মাকা-নূবিহী ইয়াছতাহঝিউন।"
      },
      {
        "numberInSurah": 42,
        "pronunciation": "কুল মাই ইয়াকলাউকুম বিল লাইলি ওয়ান নাহা-রি মিনার রাহমা-নি বাল হুম ‘আন যিকরি রাব্বিহিম মু‘রিদূন।"
      },
      {
        "numberInSurah": 43,
        "pronunciation": "আম লাহুম আ-লিহাতুন তামনা‘উহুম মিন দূ নিনা- লা ইয়াছতাতী‘উনা নাছরা আনফুছিহিম ওয়ালা-হুম মিন্না-ইউছহাবূন।"
      },
      {
        "numberInSurah": 44,
        "pronunciation": "বাল মাত্তা‘না-হাউলাই ওয়া আ-বাআহুম হাত্তা-তা-লা ‘আলাইহিমুল ‘উমরু আফালা-ইয়ারাওনা আন্না-না’তিল আরদা নানকুসুহা-মিন আতরা-ফিহা- আফাহুমুল গা-লিবূন।"
      },
      {
        "numberInSurah": 45,
        "pronunciation": "কুল ইন্নামাউনযিরুকুম বিল ওয়াহয়ি  ওয়ালা-ইয়াছমা‘উসসুম্মুদ দু‘আআ ইযা-মাইউনযারূন।"
      },
      {
        "numberInSurah": 46,
        "pronunciation": "ওয়ালাইম মাছছাতহুম নাফহাতুমমিন‘আযা-বি রাব্বিকা লাইয়াকূলুন্না ইয়াওয়াইলানাইন্না-কুন্না-জা-লিমীন।"
      },
      {
        "numberInSurah": 47,
        "pronunciation": "ওয়া নাদা‘উল মাওয়া-ঝীনাল কিছতা লিইয়াওমিল কিয়া-মাতি ফালা-তুজলামুনাফছুন শাইআ- ওয়া ইন কা-না মিছকা-লা হাব্বাতিম মিন খারদালিন আতাইনা-বিহা- ওয়াকাফা-বিনা-হা-ছিবীন।"
      },
      {
        "numberInSurah": 48,
        "pronunciation": "ওয়া লাকাদ আ-তাইনা-মূছা-ওয়া হা-রূনাল ফুরকা-না ওয়া দিয়াআওঁ ওয়া যিকরাল লিলমুত্তাকীন।"
      },
      {
        "numberInSurah": 49,
        "pronunciation": "আল্লাযীনা ইয়াখশাওনা রাব্বাহুম বিলগাইবি ওয়া হুম মিনাছছা-‘আতি মুশফিকূন।"
      },
      {
        "numberInSurah": 50,
        "pronunciation": "ওয়া হা-যা-যিকরুমমুবা-রাকুন আনঝালনা-হু আফাআনতুম লাহূমুনকিরূন।"
      },
      {
        "numberInSurah": 51,
        "pronunciation": "ওয়া লাকাদ আ-তাইনাইবরা-হীমা রুশদাহূমিন কাবলুওয়া কুন্না-বিহী ‘আ-লিমীন।"
      },
      {
        "numberInSurah": 52,
        "pronunciation": "ইযকা-লা লিআবীহি ওয়া কাওমিহী মা-হা-যিহিততামা-ছীলুল্লাতীআনতুম লাহা-‘আকিফূন।"
      },
      {
        "numberInSurah": 53,
        "pronunciation": "কা-লূওয়াজাদনাআ-বাআনা-লাহা-‘আ-বিদীন।"
      },
      {
        "numberInSurah": 54,
        "pronunciation": "কা-লা লাকাদ কুনতুম আনতুম ওয়া আ-বাউকুম ফী দালা-লিম মুবীন।"
      },
      {
        "numberInSurah": 55,
        "pronunciation": "কা-লূআজি’তানা-বিলহাক্কিআম আনতা মিনাল্লা-‘ইবীন।"
      },
      {
        "numberInSurah": 56,
        "pronunciation": "কা-লা বার রাব্বুকুম রাব্বুছ ছামা-ওয়া-তি ওয়াল আরদিল্লাযী ফাতারাহুন্না  ওয়া আনা ‘আলা-যা-লিকুম মিনাশশা-হিদীন।"
      },
      {
        "numberInSurah": 57,
        "pronunciation": "ওয়া তাল্লা-হি লাআকীদান্না আসনা-মাকুম বা‘দা আন তুওয়াললূমুদবিরীন।"
      },
      {
        "numberInSurah": 58,
        "pronunciation": "ফাজা‘আলাহুম জুযা-যান ইল্লা-কাবীরাল লাহুম লা‘আল্লাহুম ইলাইহি ইয়ারজি‘ঊন।"
      },
      {
        "numberInSurah": 59,
        "pronunciation": "কা-লূমান ফা‘আলা হা-যা বিআ-লিহাতিনাইন্নাহূলামিনাজ্জা-লিমীন।"
      },
      {
        "numberInSurah": 60,
        "pronunciation": "কা-লূছামি‘না ফাতাইঁ ইয়াযকুরুহুম ইউকা-লুলাহূইবরা-হীম।"
      },
      {
        "numberInSurah": 61,
        "pronunciation": "কা-লূফা’তূবিহী ‘আলাআ‘ইউনিন্না-ছি লা‘আল্লাহুম ইয়াশহাদূন।"
      },
      {
        "numberInSurah": 62,
        "pronunciation": "কা-লূআআনতা ফা‘আলতা হা-যা-বিআ-লিহাতিনা ইয়াইবরা-হীম।"
      },
      {
        "numberInSurah": 63,
        "pronunciation": "কা-লা বাল ফা‘আলাহূ  কাবীরুহুম হা-যা-ফাছআলূহুম ইন কা-নূইয়ানতিকূন।"
      },
      {
        "numberInSurah": 64,
        "pronunciation": "ফারাজা‘উইলাআনফুছিহিম ফাকা-লূইন্নাকুম আনতুমুজ্জা-লিমূন।"
      },
      {
        "numberInSurah": 65,
        "pronunciation": "ছু ম্মা নুকিছূ‘আলা-রুঊছিহিম লাকাদ ‘আলিমতা মা-হাউলাই ইয়ানতিকূন।"
      },
      {
        "numberInSurah": 66,
        "pronunciation": "কা-লা আফাতা‘বুদূনা মিন দূনিল্লা-হি মা-লা-ইয়ানফা‘উকুম শাইআওঁ ওয়ালা-ইয়াদু ররুকুম।"
      },
      {
        "numberInSurah": 67,
        "pronunciation": "উফফিল্লাকুম ওয়া লিমা-তা‘বুদূ না মিন দূ নিল্লা-হি আফালা-তা‘কিলূন।"
      },
      {
        "numberInSurah": 68,
        "pronunciation": "কা-লূহাররিকূহু ওয়ানসুরূআ-লিহাতাকুম ইন কুনতুম ফা-‘ইলীন।"
      },
      {
        "numberInSurah": 69,
        "pronunciation": "কুলনা-ইয়া-না-রু কূনী বারদাওঁ ওয়া ছালা-মান ‘আলাইবরা-হীম।"
      },
      {
        "numberInSurah": 70,
        "pronunciation": "ওয়া আরা-দূবিহী কাইদান ফাজা‘আলনা-হুমুল আখছারীন।"
      },
      {
        "numberInSurah": 71,
        "pronunciation": "ওয়া নাজ্জাইনা-হু ওয়া লূতান ইলাল আরদিল্লাতী বা-রাকনা-ফীহা-লিল‘আ-লামীন।"
      },
      {
        "numberInSurah": 72,
        "pronunciation": "ওয়া ওয়াহাবনা-লাহূইছহা-কা ওয়া ইয়া‘কূবা নাফিলাতাও ওয়া কুল্লান জা‘আলনা-সা-লিহীন ।"
      },
      {
        "numberInSurah": 73,
        "pronunciation": "ওয়া জাআলনা-হুম আইম্মাতাইঁ ইয়াহদূ না বিআমরিনা-ওয়াআওহাইনাইলাইহিম ফি‘লাল খাইরা-তি ওয়া ইকা-মাসসালা-তি ওয়া ঈতাআঝঝাকা-তি ওয়া কা-নূলানা-‘আবিদীন ।"
      },
      {
        "numberInSurah": 74,
        "pronunciation": "ওয়া লূতান আ-তাইনা-হু হুকমাওঁ ওয়া ‘ইল মাওঁ ওয়া নাজ্জাইনা-হু মিনাল কারয়াতিল্লাতী কা-নাত তা‘মালুল খাবাইছা ইন্নাহুম কা-নূকাওমা ছাওইন ফা-ছিকীন।"
      },
      {
        "numberInSurah": 75,
        "pronunciation": "ওয়া আদখাল না-হু ফী রাহমাতিনা- ইন্নাহূমিনাসসা-লিহীন।"
      },
      {
        "numberInSurah": 76,
        "pronunciation": "ওয়া নূহান ইযনা-দা-মিন কাবলুফাছতাজাবনা-লাহূফানাজ্জাইনা-হুওয়াআহলাহূমিনাল কারবিল ‘আজীম।"
      },
      {
        "numberInSurah": 77,
        "pronunciation": "ওয়া নাসারনা-হু মিনাল কাওমিল্লাযীনা কাযযাবূবিআ-য়া-তিনা- ইন্নাহুম কা-নূ কাওমা ছাওইন ফাআগরাকনা-হুম আজমা‘ঈন।"
      },
      {
        "numberInSurah": 78,
        "pronunciation": "ওয়া দাঊদা ওয়া ছুলাইমা-না ইযইয়াহকুমা-নি ফিল হারছি ইযনাফাশাত ফীহি গানামুল কাওমি ওয়াকুন্না-লিহুকমিহিম শা-হিদীন।"
      },
      {
        "numberInSurah": 79,
        "pronunciation": "ফাফাহহামনা-হা-ছুলাইমা-না ওয়া কুল্লান আ-তাইনা-হুকমাও ওয়া ‘ইলমাওঁ  ওয়া ছাখখারনা-মা‘আ দা-ঊদাল জিবা-লা ইউছাব্বিহনা ওয়াততাইরা ওয়া কুন্না-ফা‘ইলীন ।"
      },
      {
        "numberInSurah": 80,
        "pronunciation": "ওয়া ‘আল্লামনা-হু সান‘আতা লাবূছিল লাকুম লিতুহছিনাকুম মিম বা’ছিকুম ফাহাল আনতুম শা-কিরূন।"
      },
      {
        "numberInSurah": 81,
        "pronunciation": "ওয়া লিছুলাইমা-নাররীহা ‘আ-সিফাতান তাজরী বিআমরিহীইলাল আরদিল্লাতী বা-রাকনাফীহা- ওয়াকুন্না-বিকুল্লি শাইয়িন ‘আ-লিমীন।"
      },
      {
        "numberInSurah": 82,
        "pronunciation": "ওয়া মিনাশশাইয়া-তীনি মাইঁ ইয়াগূছূনা লাহূওয়া ইয়া‘মালূনা ‘আমালান দূ না যা-লিকা ওয়া কুন্না-লাহুম হাফিজীন ।"
      },
      {
        "numberInSurah": 83,
        "pronunciation": "ওয়া আইঁয়ুবা ইযনা-দা-রাব্বাহূআন্নী মাছছানিয়াদদু ররু ওয়া আনতা আরহামুররা-হিমীন ।"
      },
      {
        "numberInSurah": 84,
        "pronunciation": "ফাছতাজাবনা- লাহূফাকাশাফনা-মা-বিহী মিন দু ররিওঁ ওয়া আ-তাইনা-হু আহলাহূওয়া মিছলাহুম মা‘আহুম রাহমাতাম মিন ‘ইনদিনা-ওয়া যিকরা-লিল‘আ-বিদীন।"
      },
      {
        "numberInSurah": 85,
        "pronunciation": "ওয়া ইছমা-‘ঈলা ওয়া ইদরীছা ওয়া যাল কিফলি কুল্লুম মিনাসসা-বিরীন।"
      },
      {
        "numberInSurah": 86,
        "pronunciation": "ওয়া আদখাল না-হুম ফী রাহমাতিনা-  ইন্নাহুম মিনাসসা-লিহীন।"
      },
      {
        "numberInSurah": 87,
        "pronunciation": "ওয়া যাননূনি ইযযাহাবা মুগা-দিবান ফাজান্না আল্লান নাকদিরা ‘আলাইহি ফানা-দাফিজজু লুমা-তি আল্লাইলা-হা ইল্লাআনতা ছুবহা-নাকা  ইন্নী কুনতুমিনাজ্জালিমীন।"
      },
      {
        "numberInSurah": 88,
        "pronunciation": "ফাছতাজাবনা-লাহূওয়া নাজ্জাইনা-হু মিনাল গাম্মি ওয়া কাযা-লিকা নুনজিল মু’মিনীন।"
      },
      {
        "numberInSurah": 89,
        "pronunciation": "ওয়া ঝাকারিইইয়াইযনা-দা-রাব্বাহূরাব্বি লা-তাযারনী ফারদাওঁ ওয়া আনতা খাইরুল ওয়ারিছীন।"
      },
      {
        "numberInSurah": 90,
        "pronunciation": "ফছতাজাবনা-লাহূ  ওয়া ওয়াহাবনা-লাহূইয়াহইয়া-ওয়া আসলাহনা-লাহূঝাওজাহূ ইন্নাহুম কা-নূইউছা-রি‘ঊনা ফিল খাইরা-তি ওয়া ইয়াদঊনানা-রাগাবাওঁ ওয়া রাহাবাও ওয়া কা-নূলানা-খা-শি‘ঈন।"
      },
      {
        "numberInSurah": 91,
        "pronunciation": "ওয়াল্লাতীআহসানাত ফারজাহা-ফানাফাখনা-ফীহা-মির রূহিনা-ওয়া জা‘আলনা-হাওয়াবনাহাআ-য়াতাল লিল‘আ-লামীন।"
      },
      {
        "numberInSurah": 92,
        "pronunciation": "ইন্না হা-যিহীউম্মাতুকুম উম্মাতাওঁ  ওয়া-হিদাতাওঁ ওয়া আনা রাব্বুকুম ফা‘বুদূ ন।"
      },
      {
        "numberInSurah": 93,
        "pronunciation": "ওয়া তাকাততা‘ঊআমরাহুম বাইনাহুম কুল্লুন ইলাইনা-রা-জি‘উন।"
      },
      {
        "numberInSurah": 94,
        "pronunciation": "ফামাইঁ ইয়া‘মাল মিনাসসা-লিহা-তি ওয়া হুওয়া মু’মিনুন ফালা কুফরা-না লিছা‘য়িহী ওয়া ইন্না-লাহূকা-তিবূন।"
      },
      {
        "numberInSurah": 95,
        "pronunciation": "ওয়া হারা-মুন ‘আলা-কারইয়াতিন আহলাকনা-হাআন্নাহুম লা-ইয়ারজি‘ঊন।"
      },
      {
        "numberInSurah": 96,
        "pronunciation": "হাত্তাইযা-ফুতিহাত ইয়া’জুজুওয়ামা’জুজুওয়া হুম মিন কুল্লি হাদাবিইঁ ইয়ানছিলূন।"
      },
      {
        "numberInSurah": 97,
        "pronunciation": "ওয়াকতালাবাল ওয়া‘দুল হাক্কুফাইযা-হিয়া শা-খিসাতুন আবসা-রুল্লাযীনা কাফারূ ইয়া-ওয়াইলানা-কাদ কুন্না-ফী গাফলাতিম মিন হা-যা-বাল কুন্না-জা-লিমীন।"
      },
      {
        "numberInSurah": 98,
        "pronunciation": "ইন্নাকুম ওয়ামা-তা‘বুদূ না মিন দূ নিল্লা-হি হাসাবুজাহান্নামা আনতুম লাহা-ওয়া-রিদূ ন।"
      },
      {
        "numberInSurah": 99,
        "pronunciation": "লাও কা-না হাঊলাই আ-লিহাতামমা-ওয়ারাদূ হা- ওয়া কুল্লুন ফীহা-খা-লিদূ ন।"
      },
      {
        "numberInSurah": 100,
        "pronunciation": "লাহুম ফীহা-ঝাফীরুওঁ ওয়াহুম ফীহা-লা-ইয়াছমা‘ঊন।"
      },
      {
        "numberInSurah": 101,
        "pronunciation": "ইন্নাল্লাযীনা ছাবাকাত লাহুম মিন্নাল হুছনা উলাইকা ‘আনহা-মুব‘আদূ ন।"
      },
      {
        "numberInSurah": 102,
        "pronunciation": "লা-ইয়াছমা‘ঊনা হাছীছাহা- ওয়া হুম ফী মাশতাহাত আনফুছুহুম খা-লিদূ ন।"
      },
      {
        "numberInSurah": 103,
        "pronunciation": "লা-ইয়াহঝুনুহুমুল ফাঝা‘উল আকবারু ওয়া তাতালাক্কা-হুমুল মালাইকাতু হা-যাইয়াওমুকুমুল্লাযী কুনতুম তূ‘আদূ ন।"
      },
      {
        "numberInSurah": 104,
        "pronunciation": "ইয়াওমা নাতবিছছামাআ কাতাইয়িছছিজিলিল লিলকুতুবি কামা-বাদা’নাআওয়ালা খালকিন নু‘ঈদুহূ ওয়া‘দান ‘আলাইনা- ইন্না-কুন্না-ফা-‘ইলীন ।"
      },
      {
        "numberInSurah": 105,
        "pronunciation": "ওয়া লাকাদ কাতাবনা-ফিঝঝাবূরি মিম বা‘দিযযিকরি আন্নাল আরদা ইয়ারিছু হা-ইবা দিয়াসসা-লিহূন।"
      },
      {
        "numberInSurah": 106,
        "pronunciation": "ইন্না ফী হা-যা-লাবালা-গাল লিকাওমিন ‘আ-বিদীন।"
      },
      {
        "numberInSurah": 107,
        "pronunciation": "ওয়ামাআরছালনা-কা ইল্লা-রাহমাতাল লিল‘আ-লামীন।"
      },
      {
        "numberInSurah": 108,
        "pronunciation": "কুল ইন্নামা-ইঊহাইলাইয়া আন্নামাইলা-হুকুম ইলা-হুওঁ ওয়াহিদুন ফাহাল আনতুম মুছলিমূন।"
      },
      {
        "numberInSurah": 109,
        "pronunciation": "ফাইন তাওয়াল্লাও ফাকুল আ-যানতুকুম ‘আলা-ছাওয়াইও ওয়া ইন আদরীআকারীবুন আম বা‘ঈদুম মা-তূ‘আদূ ন।"
      },
      {
        "numberInSurah": 110,
        "pronunciation": "ইন্নাহূইয়া‘লামুল জাহরা মিনাল কাওলি ওয়া ইয়া‘লামুমা-তাকতুমূন।"
      },
      {
        "numberInSurah": 111,
        "pronunciation": "ওয়া ইন আদরী লা‘আল্লাহূফিতনাতুল লাকুম ওয়া মাতা-‘উন ইলা-হীন।"
      },
      {
        "numberInSurah": 112,
        "pronunciation": "কা-লা রাব্বিহকুম বিলহাক্কি ওয়া রাব্বুনার রাহমা-নুল মুছতা‘আ-নু‘আলা-মাতাসিফূন।"
      }
    ]
  }
}